{
    "controller": [
        {
            "name": "android",
            "type": "Adb"
        },
        {
            "name": "desktop",
            "type": "Win32",
            "win32": {
                "class_regex": ".*",
                "window_regex": "Visual Studio"
            }
        }
    ],
    "resource": [
        {
            "name": "official",
            "path": [
                "{PROJECT_DIR}/resource"
            ]
        }
    ],
    "task": [
        {
            "name": "OCRCity",
            "entry": "OCRCity"
        },
        {
            "name": "OCRToExcel",
            "entry": "OCRToExcel"
        }
    ],
    "option": {
    }
}
